chessnake/__init__.py
chessnake/chesslib/Chess.py
chessnake/chesslib/ChessError.py
chessnake/chesslib/ChessImg.py
chessnake/chesslib/Game.py
chessnake/chesslib/__init__.py
chessnake/chesslib/data/Roboto-Black.ttf
chessnake/chesslib/data/init.sql
chessnake/chesslib/data/img/0.png
chessnake/chesslib/data/img/1.png
chessnake/chesslib/data/img/B0.png
chessnake/chesslib/data/img/B1.png
chessnake/chesslib/data/img/K0.png
chessnake/chesslib/data/img/K1.png
chessnake/chesslib/data/img/N0.png
chessnake/chesslib/data/img/N1.png
chessnake/chesslib/data/img/P0.png
chessnake/chesslib/data/img/P1.png
chessnake/chesslib/data/img/Q0.png
chessnake/chesslib/data/img/Q1.png
chessnake/chesslib/data/img/R0.png
chessnake/chesslib/data/img/R1.png
chessnake/chesslib/data/img/a.png
chessnake/chesslib/data/img/b.png
chessnake/chesslib/data/img/blankboard.png
chessnake/chesslib/data/img/c.png
chessnake/chesslib/data/img/d.png
chessnake/chesslib/data/img/e.png
chessnake/chesslib/data/img/f.png
chessnake/chesslib/data/img/g.png
chessnake/chesslib/data/img/h.png
chessnake/chesslib/data/img/num1.png
chessnake/chesslib/data/img/num2.png
chessnake/chesslib/data/img/num3.png
chessnake/chesslib/data/img/num4.png
chessnake/chesslib/data/img/num5.png
chessnake/chesslib/data/img/num6.png
chessnake/chesslib/data/img/num7.png
chessnake/chesslib/data/img/num8.png
chessnake/chesslib/data/img/orange.png
chessnake/chesslib/data/img/template.png
chessnake/postgres/Game.py
chessnake/postgres/GameError.py
chessnake/postgres/Sql_Utils.py
chessnake/postgres/__init__.py
chessnake-0.3.1.dist-info/LICENSE
chessnake-0.3.1.dist-info/METADATA
chessnake-0.3.1.dist-info/WHEEL
chessnake-0.3.1.dist-info/top_level.txt
chessnake-0.3.1.dist-info/RECORD
